sautech/__init__.py
sautech/stt/__init__.py
sautech/stt/constants.py
sautech/stt/protocol.py
sautech/stt/types.py
sautech/stt/fasttranscription/__init__.py
sautech/stt/fasttranscription/client.py
sautech/stt/realtime/__init__.py
sautech/stt/realtime/client.py
sautech-0.7.0.dist-info/METADATA
sautech-0.7.0.dist-info/WHEEL
sautech-0.7.0.dist-info/top_level.txt
sautech-0.7.0.dist-info/RECORD
