Metadata-Version: 2.4
Name: sautech
Version: 0.7.0
Summary: Python SDK for SauTech ASR Services
Requires-Python: >=3.9
Requires-Dist: aiohttp>=3.12.15
Requires-Dist: loguru>=0.7.3
Requires-Dist: pydantic>=2.11.7
Requires-Dist: python-socketio[client]>=5.13.0
Requires-Dist: websockets>=15.0.1
